bootstrap.py
buildout.cfg
setup.cfg
setup.py
collective/__init__.py
collective.recipe.linktally.egg-info/PKG-INFO
collective.recipe.linktally.egg-info/SOURCES.txt
collective.recipe.linktally.egg-info/dependency_links.txt
collective.recipe.linktally.egg-info/entry_points.txt
collective.recipe.linktally.egg-info/namespace_packages.txt
collective.recipe.linktally.egg-info/not-zip-safe
collective.recipe.linktally.egg-info/requires.txt
collective.recipe.linktally.egg-info/top_level.txt
collective/recipe/__init__.py
collective/recipe/linktally/README.txt
collective/recipe/linktally/__init__.py
collective/recipe/linktally/linktally.conf.template
collective/recipe/linktally/runtally.py
collective/recipe/linktally/runtests.py
collective/recipe/linktally/docs/README.txt
collective/recipe/linktally/tests/__init__.py
collective/recipe/linktally/tests/test_docs.py
