Metadata-Version: 1.0
Name: collective.recipe.linktally
Version: 0.1.0-2
Summary: zc.buildout recipe for setting up linktally
Home-page: https://svn.plone.org/svn/collective/buildout/collective.recipe.linktally/
Author: Rocky Burt
Author-email: rocky@serverzen.com
License: GPL
Keywords: buildout linktally
Platform: UNKNOWN
Classifier: Programming Language :: Python
Classifier: Topic :: Software Development :: Libraries :: Python Modules
